__init__.py
web3cli/.DS_Store
web3cli/.mypy_cache/.gitignore
web3cli/.mypy_cache/3.10/@plugins_snapshot.json
web3cli/.mypy_cache/3.10/_ast.data.json
web3cli/.mypy_cache/3.10/_ast.meta.json
web3cli/.mypy_cache/3.10/_codecs.data.json
web3cli/.mypy_cache/3.10/_codecs.meta.json
web3cli/.mypy_cache/3.10/_collections_abc.data.json
web3cli/.mypy_cache/3.10/_collections_abc.meta.json
web3cli/.mypy_cache/3.10/_decimal.data.json
web3cli/.mypy_cache/3.10/_decimal.meta.json
web3cli/.mypy_cache/3.10/_random.data.json
web3cli/.mypy_cache/3.10/_random.meta.json
web3cli/.mypy_cache/3.10/_typeshed/__init__.data.json
web3cli/.mypy_cache/3.10/_typeshed/__init__.meta.json
web3cli/.mypy_cache/3.10/abc.data.json
web3cli/.mypy_cache/3.10/abc.meta.json
web3cli/.mypy_cache/3.10/ast.data.json
web3cli/.mypy_cache/3.10/ast.meta.json
web3cli/.mypy_cache/3.10/builtins.data.json
web3cli/.mypy_cache/3.10/builtins.meta.json
web3cli/.mypy_cache/3.10/codecs.data.json
web3cli/.mypy_cache/3.10/codecs.meta.json
web3cli/.mypy_cache/3.10/collections/__init__.data.json
web3cli/.mypy_cache/3.10/collections/__init__.meta.json
web3cli/.mypy_cache/3.10/collections/abc.data.json
web3cli/.mypy_cache/3.10/collections/abc.meta.json
web3cli/.mypy_cache/3.10/contextlib.data.json
web3cli/.mypy_cache/3.10/contextlib.meta.json
web3cli/.mypy_cache/3.10/dataclasses.data.json
web3cli/.mypy_cache/3.10/dataclasses.meta.json
web3cli/.mypy_cache/3.10/decimal.data.json
web3cli/.mypy_cache/3.10/decimal.meta.json
web3cli/.mypy_cache/3.10/email/__init__.data.json
web3cli/.mypy_cache/3.10/email/__init__.meta.json
web3cli/.mypy_cache/3.10/email/charset.data.json
web3cli/.mypy_cache/3.10/email/charset.meta.json
web3cli/.mypy_cache/3.10/email/contentmanager.data.json
web3cli/.mypy_cache/3.10/email/contentmanager.meta.json
web3cli/.mypy_cache/3.10/email/errors.data.json
web3cli/.mypy_cache/3.10/email/errors.meta.json
web3cli/.mypy_cache/3.10/email/header.data.json
web3cli/.mypy_cache/3.10/email/header.meta.json
web3cli-1.1.36.dist-info/entry_points.txt
web3cli-1.1.36.dist-info/WHEEL
web3cli-1.1.36.dist-info/METADATA
web3cli-1.1.36.dist-info/licenses/LICENSE
web3cli-1.1.36.dist-info/RECORD
