Metadata-Version: 2.1
Name: web3cli
Version: 1.1.36
Summary: Interact with blockchains and smart contracts using the command line
License: MIT
Keywords: web3,w3,cli,evm,blockchain,ethereum,binance,avalanche
Author-email: coccoinomane <coccoinomane@gmail.com>
Requires-Python: >=3.9
Requires-Dist: cement>=3.0.10
Requires-Dist: cement[colorlog]>=3.0.10
Requires-Dist: cement[jinja2]>=3.0.10
Requires-Dist: cement[tabulate]>=3.0.10
Requires-Dist: cement[yaml]>=3.0.10
Requires-Dist: cryptography>=38.0.3
Requires-Dist: eth-account>=0.8.0
Requires-Dist: peewee>=3.15.3
Requires-Dist: ruamel.yaml>=0.17.21
Requires-Dist: web3>=6.0.0
Requires-Dist: web3client>=1.3.10
Project-URL: homepage, https://github.com/coccoinomane/web3cli
Project-URL: repository, https://github.com/coccoinomane/web3cli
